feynamp/__init__.py
feynamp/amplitude.py
feynamp/form/__init__.py
feynamp/form/color.py
feynamp/form/colorh.py
feynamp/form/form.py
feynamp/form/lorentz.py
feynamp/form/momentum.py
feynamp/leg.py
feynamp/log.py
feynamp/math.py
feynamp/momentum.py
feynamp/propagator.py
feynamp/sympy/__init__.py
feynamp/sympy/color.py
feynamp/sympy/lorentz.py
feynamp/test/__init__.py
feynamp/test/colorcorrelation.py
feynamp/test/spincorrelation.py
feynamp/util.py
feynamp/vertex.py
feynamp-0.0.12.dist-info/LICENSE
feynamp-0.0.12.dist-info/WHEEL
feynamp-0.0.12.dist-info/METADATA
feynamp-0.0.12.dist-info/RECORD
