Metadata-Version: 2.1
Name: feynamp
Version: 0.0.12
Summary: Compute Feynman diagrams
Home-page: https://github.com/APN-Pucky/feynamp
Author: Alexander Puck Neuwirth
Author-email: alexander@neuwirth-informatik.de
Requires-Python: >=3.8,<4.0
Classifier: Programming Language :: Python :: 3
Classifier: Programming Language :: Python :: 3.8
Classifier: Programming Language :: Python :: 3.9
Classifier: Programming Language :: Python :: 3.10
Classifier: Programming Language :: Python :: 3.11
Requires-Dist: feynml (>=0.2.26)
Requires-Dist: feynmodel (>=0.0.9)
Requires-Dist: pqdm
Requires-Dist: python-form
Requires-Dist: sympy
Project-URL: Repository, https://github.com/APN-Pucky/feynamp
